Matplotlib30MijiChuyi/README.md
Matplotlib30MijiChuyi/__init__.py
Matplotlib30MijiChuyi/__main__.py
Matplotlib30MijiChuyi/file.epub
Matplotlib30MijiChuyi/index.html
Matplotlib30MijiChuyi/css/__init__.py
Matplotlib30MijiChuyi/css/annotations.css
Matplotlib30MijiChuyi/css/main.css
Matplotlib30MijiChuyi/css/normalize.css
Matplotlib30MijiChuyi/css/popup.css
Matplotlib30MijiChuyi/font/__init__.py
Matplotlib30MijiChuyi/font/fontello.eot
Matplotlib30MijiChuyi/font/fontello.svg
Matplotlib30MijiChuyi/font/fontello.ttf
Matplotlib30MijiChuyi/font/fontello.woff
Matplotlib30MijiChuyi/img/__init__.py
Matplotlib30MijiChuyi/img/annotator-glyph-sprite.png
Matplotlib30MijiChuyi/img/annotator-icon-sprite.png
Matplotlib30MijiChuyi/img/apple-touch-icon.png
Matplotlib30MijiChuyi/img/cancelfullscreen.png
Matplotlib30MijiChuyi/img/close.png
Matplotlib30MijiChuyi/img/fullscreen.png
Matplotlib30MijiChuyi/img/loader.gif
Matplotlib30MijiChuyi/img/menu-icon.png
Matplotlib30MijiChuyi/img/save.png
Matplotlib30MijiChuyi/img/saved.png
Matplotlib30MijiChuyi/img/settings-s.png
Matplotlib30MijiChuyi/img/settings.png
Matplotlib30MijiChuyi/img/star.png
Matplotlib30MijiChuyi/js/__init__.py
Matplotlib30MijiChuyi/js/epub.js
Matplotlib30MijiChuyi/js/epub.min.js
Matplotlib30MijiChuyi/js/epub.min.map
Matplotlib30MijiChuyi/js/hooks.min.js
Matplotlib30MijiChuyi/js/hooks.min.map
Matplotlib30MijiChuyi/js/reader.js
Matplotlib30MijiChuyi/js/reader.js.map
Matplotlib30MijiChuyi/js/reader.min.js
Matplotlib30MijiChuyi/js/reader.min.map
Matplotlib30MijiChuyi/js/hooks/__init__.py
Matplotlib30MijiChuyi/js/hooks/extensions/__init__.py
Matplotlib30MijiChuyi/js/hooks/extensions/highlight.js
Matplotlib30MijiChuyi/js/libs/__init__.py
Matplotlib30MijiChuyi/js/libs/jquery.min.js
Matplotlib30MijiChuyi/js/libs/localforage.min.js
Matplotlib30MijiChuyi/js/libs/screenfull.js
Matplotlib30MijiChuyi/js/libs/screenfull.min.js
Matplotlib30MijiChuyi/js/libs/zip.min.js
Matplotlib30MijiChuyi/js/plugins/__init__.py
matplotlib_3_0_miji_chuyi-2024.3.5.0.dist-info/METADATA
matplotlib_3_0_miji_chuyi-2024.3.5.0.dist-info/WHEEL
matplotlib_3_0_miji_chuyi-2024.3.5.0.dist-info/entry_points.txt
matplotlib_3_0_miji_chuyi-2024.3.5.0.dist-info/top_level.txt
matplotlib_3_0_miji_chuyi-2024.3.5.0.dist-info/RECORD
